LICENSE
MANIFEST.in
README.md
VERSION
setup.py
obob_condor/__init__.py
obob_condor/job.py
obob_condor/jobcluster.py
obob_condor.egg-info/PKG-INFO
obob_condor.egg-info/SOURCES.txt
obob_condor.egg-info/dependency_links.txt
obob_condor.egg-info/requires.txt
obob_condor.egg-info/top_level.txt
obob_condor/jinja2_templates/runner.py
obob_condor/jinja2_templates/submit.sub