Metadata-Version: 2.1
Name: obob-condor
Version: 0.0.1
Summary: Convenient Python Abstraction for the Condor cluster at the PLUS
Home-page: https://gitlab.com/obob/obob_condor
Author: Thomas Hartmann
Author-email: thomas.hartmann@th-ht.de
License: GPL3
Keywords: HTCondor
Platform: UNKNOWN
Classifier: Development Status :: 4 - Beta
Classifier: Intended Audience :: Science/Research
Classifier: License :: OSI Approved :: GNU General Public License v3 or later (GPLv3+)
Classifier: Operating System :: OS Independent
Classifier: Programming Language :: Python
